MANIFEST.in
setup.py
scatologist/__init__.py
scatologist/logrow.py
scatologist/main.py
scatologist/readers.py
scatologist/readme.txt
scatologist/utilities.py
scatologist/version.txt
scatologist.egg-info/PKG-INFO
scatologist.egg-info/SOURCES.txt
scatologist.egg-info/dependency_links.txt
scatologist.egg-info/not-zip-safe
scatologist.egg-info/requires.txt
scatologist.egg-info/top_level.txt
scatologist/components/__init__.py
scatologist/components/categoriser.py
scatologist/components/counter.py
scatologist/components/histogram.py
scatologist/components/sorter.py
scatologist/components/writer.py