Metadata-Version: 1.0
Name: scatologist
Version: 0.1
Summary: A framework for ad hoc analysis and reporting from log files.
Home-page: http://pypi.python.org/pypi/scatologist
Author: Chris Withers
Author-email: chris@simplistix.co.uk
License: MIT
Platform: UNKNOWN
Classifier: Development Status :: 4 - Beta
Classifier: Intended Audience :: Developers
Classifier: License :: OSI Approved :: MIT License
